arcade_abcdefg/__init__.py
arcade_abcdefg/tools/__init__.py
arcade_abcdefg/tools/hello.py
arcade_abcdefg-0.0.1.dist-info/LICENSE
arcade_abcdefg-0.0.1.dist-info/METADATA
arcade_abcdefg-0.0.1.dist-info/WHEEL
arcade_abcdefg-0.0.1.dist-info/RECORD
